llama_ipfs/__init__.py
llama_ipfs/__main__.py
llama_ipfs/_version.py
llama_ipfs/patch.py
llama_ipfs/py.typed
llama_ipfs-0.2.0.dist-info/METADATA
llama_ipfs-0.2.0.dist-info/WHEEL
llama_ipfs-0.2.0.dist-info/entry_points.txt
llama_ipfs-0.2.0.dist-info/top_level.txt
llama_ipfs-0.2.0.dist-info/RECORD
