Metadata-Version: 2.4
Name: llama-ipfs
Version: 0.2.0
Summary: Enable IPFS model loading for llama-cpp-python
Author-email: Alex Baker <alex.baker.fon@protonmail.com>
License: MIT
Project-URL: Homepage, https://github.com/alexbakers/llama_ipfs
Project-URL: Bug Tracker, https://github.com/alexbakers/llama_ipfs/issues
Keywords: llama-cpp-python,ipfs,utility
Classifier: Development Status :: 4 - Beta
Classifier: Intended Audience :: Developers
Classifier: Programming Language :: Python :: 3
Classifier: Programming Language :: Python :: 3.8
Classifier: Programming Language :: Python :: 3.9
Classifier: Programming Language :: Python :: 3.10
Classifier: Programming Language :: Python :: 3.11
Classifier: Programming Language :: Python :: 3.12
Classifier: Programming Language :: Python :: 3.13
Requires-Python: >=3.8
Requires-Dist: requests>=2.25.0
Provides-Extra: dev
Requires-Dist: black; extra == "dev"
Requires-Dist: isort; extra == "dev"
Requires-Dist: mypy; extra == "dev"
Requires-Dist: pytest; extra == "dev"
Requires-Dist: flake8; extra == "dev"
